graflow/__init__.py
graflow/exceptions.py
graflow/api/README.md
graflow/api/__init__.py
graflow/api/__main__.py
graflow/api/app.py
graflow/api/main.py
graflow/api/endpoints/__init__.py
graflow/api/endpoints/feedback.py
graflow/api/endpoints/feedback_ui.py
graflow/api/schemas/__init__.py
graflow/api/schemas/feedback.py
graflow/api/templates/common/base.html
graflow/api/templates/common/error.html
graflow/api/templates/feedback/expired.html
graflow/api/templates/feedback/form.html
graflow/api/templates/feedback/list.html
graflow/api/templates/feedback/success.html
graflow/channels/__init__.py
graflow/channels/base.py
graflow/channels/factory.py
graflow/channels/memory_channel.py
graflow/channels/redis_channel.py
graflow/channels/schemas.py
graflow/channels/typed.py
graflow/coordination/__init__.py
graflow/coordination/coordinator.py
graflow/coordination/executor.py
graflow/coordination/graph_store.py
graflow/coordination/records.py
graflow/coordination/redis_coordinator.py
graflow/coordination/task_spec.py
graflow/coordination/threading_coordinator.py
graflow/core/checkpoint.py
graflow/core/context.py
graflow/core/cycle.py
graflow/core/decorators.py
graflow/core/engine.py
graflow/core/graph.py
graflow/core/handler.py
graflow/core/serialization.py
graflow/core/task.py
graflow/core/workflow.py
graflow/core/handlers/__init__.py
graflow/core/handlers/direct.py
graflow/core/handlers/docker.py
graflow/core/handlers/group_policy.py
graflow/core/handlers/templates/docker_task_runner.py
graflow/debug/__init__.py
graflow/debug/find_locks.py
graflow/hitl/__init__.py
graflow/hitl/handler.py
graflow/hitl/manager.py
graflow/hitl/types.py
graflow/hitl/backend/__init__.py
graflow/hitl/backend/base.py
graflow/hitl/backend/filesystem.py
graflow/hitl/backend/redis.py
graflow/llm/__init__.py
graflow/llm/client.py
graflow/llm/serialization.py
graflow/llm/agents/__init__.py
graflow/llm/agents/adk_agent.py
graflow/llm/agents/base.py
graflow/llm/agents/pydantic_agent.py
graflow-0.1.0.dist-info/METADATA
graflow-0.1.0.dist-info/WHEEL
graflow-0.1.0.dist-info/licenses/LICENSE
graflow-0.1.0.dist-info/RECORD
